{
    "Options": [
        {
            "0": [
                {
                    "Name": "a"
                },
                {
                    "Group": "A"
                }
            ]
        },
        {
            "1": [
                {
                    "Name": "b"
                },
                {
                    "Group": "A"
                }
            ]
        },
        {
            "2": [
                {
                    "Name": "c"
                },
                {
                    "Group": "B"
                }
            ]
        },
        {
            "3": [
                {
                    "Name": "d"
                },
                {
                    "Group": "B"
                }
            ]
        },
        {
            "4": [
                {
                    "Name": "e"
                },
                {
                    "Group": "C"
                }
            ]
        }
    ]
}